{"Course ID": "187203", "Institution": "FAMU - FLORIDA A & M UNIVERSITY", "Course Name": "ACG 2021L - FINANCIAL ACCOUNTING LAB", "Course Title": "FINANCIAL ACCOUNTING LAB", "Discipline": "165 - ACCOUNTING", "Prefix": "ACG - ACCOUNTING: GENERAL", "Level": "2", "Statewide Course": "ACCOUNTING PRIN-(CONDENSED)(3 CREDITS)", "Lab Code": "LAB", "Honors Course": "NO", "Add Date": "01/02/2011", "Effective Date": "01/02/2011", "Discontinue Date": "", "Date SCNS Approved": "1/18/2011", "Term Type": "SEMESTER", "Course Credits": "3.0", "Type of Credit": "COLLEGE CREDIT", "Clock Hours": "", "Course Status": "ACTIVE", "General Education Core": " ", "General Education Requirements": " ", "Rule 6A-10.030": "NO", "Rule 6A-10.030 Writing": "NO", "Degree Type": "BACCALAUREATE", "Prerequisites": "NONE", "Corequisites": "NONE", "Course Description": "STUDENTS WILL LEARN THE BASIC OF FINANCIAL ACCOUNTING.  THEY WILL GAIN AN UNDERSTANDING OF THE PURPOSE AND USES OF FINANCIAL ACCOUNTING , INCLUDING REAL APPLICATIONS.  THIS COURSE WILL PROVIDE A BASIC FOR ADVANCED ACCOUNTING COURSES TO FOLLOW. THE COURSE WILL ALSO BE USED AS A MEANS OF PREPARING THE STUDENT FOR SUCCESSFUL CAREER IN BUSINESS BY DEVELOPING SKILLS OF ORGANIZATION, TIME MANAGEMENT, SELF DISCIPLINE, AND COMMUNICATIONS", "Objectives / Learning Outcome(s) / Major Topics": "", "Textbook(s)": "NONE", "Transfer Status": "GUARANTEED TRANSFER TO INSTITUTION OFFERING SAME COURSE.", "Transaction Type": ""}