{"Course ID": "132382", "Institution": "SCFMS - STATE COLLEGE OF FLORIDA, MANATEE-SARASOTA", "Course Name": "ACG 2930 - SPECIAL TOPICS IN ACCOUNTING", "Course Title": "SPECIAL TOPICS IN ACCOUNTING", "Discipline": "165 - ACCOUNTING", "Prefix": "ACG - ACCOUNTING: GENERAL", "Level": "2", "Statewide Course": "SPECIAL TOPICS/SEMINARS", "Lab Code": " ", "Honors Course": "NO", "Add Date": "08/01/2005", "Effective Date": "08/01/2005", "Discontinue Date": "", "Date SCNS Approved": "10/29/2004", "Term Type": "SEMESTER", "Course Credits": "1-3", "Type of Credit": "COLLEGE CREDIT", "Clock Hours": "", "Course Status": "ACTIVE", "General Education Core": " ", "General Education Requirements": " ", "Rule 6A-10.030": "NO", "Rule 6A-10.030 Writing": "NO", "Degree Type": "A.A.S.A.S.", "Prerequisites": "NONE", "Corequisites": "NONE", "Course Description": "THIS COURSE IS DESIGNED TO MEET THE SPECIAL NEEDS OF INDIVIDUALS OR GROUPS FOR WHOM REGULARLY DESCRIBED COURSES IN ACCOUNTING MAY NOT BE AVAILABLE.  (OFFERED ONLY AS NEEDED)", "Objectives / Learning Outcome(s) / Major Topics": "SPECIFIC STUDENT PERFORMANCE OBJECTIVES ARE DEVELOPED FOR EACH STUDENT, WHICH ARE IN LINE WITH THEIR CAREER GOALS AND THE LENGTH AND TYPE OF WORK INTERNSHIP AVAILABLE.", "Textbook(s)": "NONE", "Transfer Status": "NOT AUTOMATICALLY TRANSFERABLE", "Transaction Type": ""}