{"Course ID": "226973", "Institution": "HU - HODGES UNIVERSITY", "Course Name": "ACG 3103 - INTERMEDIATE FINANCIAL REPORTING AND ANALYSIS I", "Course Title": "INTERMEDIATE FINANCIAL REPORTING AND ANALYSIS I", "Discipline": "165 - ACCOUNTING", "Prefix": "ACG - ACCOUNTING: GENERAL", "Level": "3", "Statewide Course": "INTERMEDIATE ACCOUNTING I(1 OF 3)", "Lab Code": " ", "Honors Course": "NO", "Add Date": "05/30/2018", "Effective Date": "05/30/2018", "Discontinue Date": "", "Date SCNS Approved": "6/11/2018", "Term Type": "SEMESTER", "Course Credits": "3", "Type of Credit": "COLLEGE CREDIT", "Clock Hours": "", "Course Status": "ACTIVE", "General Education Core": " ", "General Education Requirements": " ", "Rule 6A-10.030": "NO", "Rule 6A-10.030 Writing": "NO", "Degree Type": "BACCALAUREATE", "Prerequisites": "NONE", "Corequisites": "NONE", "Course Description": "THIS IS THE FIRST OF THREE INTERMEDIATE FINANCIAL REPORTING AND ANALYSIS COURSES.  IT FOCUSES ON THE THEORY, MEASUREMENT AND REPORTING STANDARDS OF GENERALLY ACCEPTED ACCOUNTING PRINCIPLES (GAAP) AND THE ONGOING HARMONIZATION PROCESS OF GAAP WITH IFRS (INTERNATIONAL FINANCIAL REPORTING STANDARDS). TOPICS INCLUDE ACCOUNTING CONCEPTS, PRONOUNCEMENTS, PROCESS, INCOME MEASUREMENTS, PRESENT VALUE CONCEPTS, CASH, RECEIVABLES, INVENTORIES, NON-CURRENT ASSETS AND CURRENT LIABILITIES. THIS COURSE MUST BE COMPLETED AT HODGES UNIVERSITY.", "Objectives / Learning Outcome(s) / Major Topics": "", "Textbook(s)": "NONE", "Transfer Status": "GUARANTEED TRANSFER TO INSTITUTION OFFERING SAME COURSE.", "Transaction Type": ""}