{"Course ID": "49553", "Institution": "UNF - UNIVERSITY OF NORTH FLORIDA", "Course Name": "ACG 2071 - PRINCIPLES OF MANAGERIAL ACCOUNTING", "Course Title": "PRINCIPLES OF MANAGERIAL ACCOUNTING", "Discipline": "165 - ACCOUNTING", "Prefix": "ACG - ACCOUNTING: GENERAL", "Level": "2", "Statewide Course": "MANAGERIAL ACCOUNTING I", "Lab Code": " ", "Honors Course": "NO", "Add Date": "", "Effective Date": "08/02/2007", "Discontinue Date": "", "Date SCNS Approved": "8/12/1996", "Term Type": "SEMESTER", "Course Credits": "3.0", "Type of Credit": "COLLEGE CREDIT", "Clock Hours": "", "Course Status": "ACTIVE", "General Education Core": " ", "General Education Requirements": " ", "Rule 6A-10.030": "NO", "Rule 6A-10.030 Writing": "NO", "Degree Type": "BACCALAUREATE", "Prerequisites": "ACG 2021 AND MAC 1105 (COLLEGE ALGEBRA) OR EQUIVALENTS EACH WITH A GRADE OF \"C\" OR BETTER.", "Corequisites": "NONE", "Course Description": "PREREQUISITE:ACG 2021 AND MAC 1105 (COLLEGE ALGEBRA) OR EQUIVALENTS EACH WITH A GRADE OF \"C\" OR BETTER.\nCONCEPTUAL INTRODUCTION TO MANAGERIAL ACCOUNTING. ACCOUNTING FOR COST REPORTING AND CONTROL. REPORTS, STATEMENTS, AND ANALYTICAL TOOLS USED BY MANAGEMENT.", "Objectives / Learning Outcome(s) / Major Topics": "", "Textbook(s)": "NONE", "Transfer Status": "GUARANTEED TRANSFER TO INSTITUTION OFFERING SAME COURSE.", "Transaction Type": ""}