{"Course ID": "176427", "Institution": "RU - RASMUSSEN UNIVERSITY", "Course Name": "ACG 3632 - AUDITING", "Course Title": "AUDITING", "Discipline": "165 - ACCOUNTING", "Prefix": "ACG - ACCOUNTING: GENERAL", "Level": "3", "Statewide Course": "AUDITING I(1 OF 2)", "Lab Code": " ", "Honors Course": "NO", "Add Date": "08/01/2010", "Effective Date": "08/01/2010", "Discontinue Date": "", "Date SCNS Approved": "3/4/2010", "Term Type": "QUARTER", "Course Credits": "4.0", "Type of Credit": "COLLEGE CREDIT", "Clock Hours": "", "Course Status": "ACTIVE", "General Education Core": " ", "General Education Requirements": " ", "Rule 6A-10.030": "NO", "Rule 6A-10.030 Writing": "NO", "Degree Type": "BACCALAUREATE", "Prerequisites": "NONE", "Corequisites": "NONE", "Course Description": "THIS COURSE INCLUDES A STUDY OF AUDITING STANDARDS AND PROCEDURES AND AN INTEGRATION OF PROFESSIONAL ETHICS WITHIN THE ACCOUNTING DISCIPLINE. EMPHASIS IS PLACED ON ANALYTICAL THINKING, EVALUATION OF BUSINESS RISKS, AND INTERNAL CONTROL PRACTICES AND A THOROUGH STUDY OF SARBANES OXLEY AS IT RELATES TO PUBLICLY TRADED COMPANIES.", "Objectives / Learning Outcome(s) / Major Topics": "", "Textbook(s)": "AUDITING-CONCEPTS FOR A CHANGING ENVIRONMENT, RITTENBERG 5E, THOMSON LEARNING, 2005\nISBN: 0-324-22310-2", "Transfer Status": "GUARANTEED TRANSFER TO INSTITUTION OFFERING SAME COURSE.", "Transaction Type": ""}