{"Course ID": "214913", "Institution": "HCC - HILLSBOROUGH COMMUNITY COLLEGE", "Course Name": "ACG 2030 - CAPSTONE REVIEW COURSE FOR ACCOUNTING PRINCIPLES", "Course Title": "CAPSTONE REVIEW COURSE FOR ACCOUNTING PRINCIPLES", "Discipline": "165 - ACCOUNTING", "Prefix": "ACG - ACCOUNTING: GENERAL", "Level": "2", "Statewide Course": "CAPSTONE REVIEW COURSE OF ACCOUNTING PRINCIPLES", "Lab Code": " ", "Honors Course": "NO", "Add Date": "08/15/2016", "Effective Date": "08/15/2016", "Discontinue Date": "", "Date SCNS Approved": "2/15/2016", "Term Type": "SEMESTER", "Course Credits": "3", "Type of Credit": "COLLEGE CREDIT", "Clock Hours": "", "Course Status": "ACTIVE", "General Education Core": " ", "General Education Requirements": " ", "Rule 6A-10.030": "NO", "Rule 6A-10.030 Writing": "NO", "Degree Type": "A.S.A.A.", "Prerequisites": "ACG 2021, ACG 2071, ACG 2100, ACG 2450, AND ACG 2630", "Corequisites": "NONE", "Course Description": "THIS COURSE GUIDES THE STUDENT IN DEALING WITH ETHICS, INTERNAL CONTROL, FRAUD AND FINANCIAL STATEMENT ANALYSIS IN THE ACCOUNTING\nENVIRONMENT, INCLUDING CONFRONTING AND RESOLVING ACCOUNTING PROBLEMS BY INTEGRATING AND APPLYING SKILLS AND TECHNIQUES ACQUIRED IN THEIR PREVIOUS COURSES, AIDING STUDENTS IN DEVELOPING A PERSONAL CODE OF ETHICS BY EXPLORING ETHICAL DILEMMAS AND PRESSURES THEY WILL FACE AS ACCOUNTANTS, AND HELPING THE STUDENT UNDERSTAND FINANCIAL STATEMENT ANALYSIS AND ITS RELATIONSHIP TO FRAUD AND FRAUD DETECTION.", "Objectives / Learning Outcome(s) / Major Topics": "1. CONFRONT AND RESOLVE ACCOUNTING PROBLEMS BY INTEGRATING AND APPLYING SKILLS AND\nTECHNIQUES ACQUIRED IN THEIR PREVIOUS COURSES.\n2. DEVELOP A PERSONAL CODE OF ETHICS BY EXPLORING ETHICAL DILEMMAS AND PRESSURES THEY WILL\nFACE AS ACCOUNTANTS.\n3. PREPARE A COMPLETE FINANCIAL STATEMENT ANALYSIS.\n4. RELATE FRAUD AND FRAUD DETECTION TO THE PREPARATION OF FINANCIAL STATEMENTS.\n5. PASS THE ACAT COMPREHENSIVE EXAMINATION FOR ACCREDITATION IN ACCOUNTANCY.", "Textbook(s)": "NONE", "Transfer Status": "GUARANTEED TRANSFER TO INSTITUTION OFFERING SAME COURSE.", "Transaction Type": ""}