{"Course ID": "141912", "Institution": "FSCJ - FLORIDA STATE COLLEGE AT JAX.", "Course Name": "ACG 2450 - ACCOUNTING USING QUICKBOOKS", "Course Title": "ACCOUNTING USING QUICKBOOKS", "Discipline": "165 - ACCOUNTING", "Prefix": "ACG - ACCOUNTING: GENERAL", "Level": "2", "Statewide Course": "BASIC COMPUTER AUGMENTED ACCOUNTING", "Lab Code": " ", "Honors Course": "NO", "Add Date": "08/01/2006", "Effective Date": "08/01/2021", "Discontinue Date": "", "Date SCNS Approved": "2/25/2020", "Term Type": "SEMESTER", "Course Credits": "3.0", "Type of Credit": "COLLEGE CREDIT", "Clock Hours": "", "Course Status": "ACTIVE", "General Education Core": " ", "General Education Requirements": " ", "Rule 6A-10.030": "NO", "Rule 6A-10.030 Writing": "NO", "Degree Type": "A.S.", "Prerequisites": "ACG 2021 AND CGS 1100C", "Corequisites": "NONE", "Course Description": "THIS COURSE IS AN INTRODUCTION TO THE INTEGRATION OF TRADITIONAL FINANCIAL ACCOUNTING PROCESSES WITH QUICKBOOKS. QUICKBOOKS WILL BE USED TO HANDLE THE BASIC GENERAL LEDGER APPLICATIONS INCLUDING GENERATING END-OF-PERIOD FINANCIAL STATEMENTS, ACCOUNTS RECEIVABLE, ACCOUNTS PAYABLE, INVENTORY AND PAYROLL.", "Objectives / Learning Outcome(s) / Major Topics": "COURSE TOPICS                                       \t\t\t\t\t \tCONTACT HOURS\n\t\t\t                                \t\t\t\t\t   \t      PER TOPIC  \n\nI.\tINTRODUCTORY COMPUTER CONCEPTS\t\t\t\t\t\t\t6\n\tA.  \tMANUAL VERSUS QUICKBOOKS\n\tB.  \tBASIC FILE MAINTENANCE (OPEN, SAVE, PRINT, BACKUP)\n\tC.  \tACCESSING AND NAVIGATING QUICKBOOKS\n\tD. \tPASSWORD PROTECTION\n\t\nII.\tCOMPANY SETUP\t\t\t\t\t\t\t\t \t7\n\tA.  \tOPEN NEW COMPANY\n\tB.  \tCREATE COMPANY PROFILE\n\tC.  \tUSING DEFAULT SETTINGS\n\tD.  \tWORK WITH EXISTING COMPANY\n\nIII.\tENTER BASIC TRANSACTION DATA                            \t\t\t\t\t9\n\tA.  \tINITIAL INVESTMENT AND COMPANY START-UP     \t\t\t\n\tB.  \tCASH TRANSACTIONS- MAKING DEPOSITS & WRITING CHECKS      \t\n\tC.  \tPRINTING DAILY REPORTS \u2013 TRIAL BALANCE                        \t\n\tD.  \tDISCOVERING AND CORRECTING ERRORS  \n\tE.  \tPREPARE ACCOUNTING WORKSHEET IN A SPREADSHEET           \t\t\t\n\nIV.\tEND-OF-PERIOD TRANSACTIONS AND REPORTING\t\t\t\t\t\t6\n\tA.  \tENTERING ADJUSTING ENTRIES\t\t\t\t\t\n\tB.  \tPRINTING FINANCIAL STATEMENTS\t\t\t\t\t\n\tC.  \tENTERING CLOSING ENTRIES\t\t\t\t\t\t\n\tD.  \tPRINTING POST-CLOSING TRIAL BALANCE \t\t\t\t\n\nV.\tCUSTOMERS AND SALES               \t\t\t\t\t\t\t8\n\tA.  \tCREATING, UPDATING & PRINTING CUSTOMER LISTS\t\t\t\n\tB.  \tBILLING & CREATING INVOICES                  \t\t\t\t\n\tC.  \tRECORDING BANK DEPOSITS \t\t                     \t\t\n\tD.  \tANALYZING ACCOUNTS RECEIVABLE                   \t\t\t\n\nVI. \tVENDORS, PURCHASES & INVENTORY\t\t\t\t\t\t\t9\n\tA.  \tCREATING PURCHASE ORDERS\n\tB.  \tRECEIVING AND PAYING BILLS\n\tC.  \tRECONCILING BANK STATEMENTS\n\tD.  \tMAINTAINING INVENTORY CONTROL\t\t                                                    \n\nVII. \tPAYROLL\t\t\t\t\t\t\t\t\t\t\t6\n\tA.  \tCREATE & MODIFY INDIVIDUAL EMPLOYEE RECORDS\n\tB.  \tPREPARE PAYROLL AND PRINT PAYCHECKS\n\tC.  \tPAY PAYROLL LIABILITIES\n\tD.  \tPRINT PAYROLL REPORTS\n\nVIII. \tCOMPLETE QUICKBOOKS PROJECT\t\t\t\t\t\t\t9", "Textbook(s)": "COMPUTER ACCOUNTING WITH QUICKBOOKS, DONNA KAY, MCGRAW HILL, LATEST EDITION.", "Transfer Status": "GUARANTEED TRANSFER TO INSTITUTION OFFERING SAME COURSE.", "Transaction Type": ""}